esp_ppq/README.md
esp_ppq/__init__.py
esp_ppq/IR/README.md
esp_ppq/IR/__init__.py
esp_ppq/IR/deploy.py
esp_ppq/IR/morph.py
esp_ppq/IR/processer.py
esp_ppq/IR/quantize.py
esp_ppq/IR/search.py
esp_ppq/IR/training.py
esp_ppq/IR/base/__init__.py
esp_ppq/IR/base/command.py
esp_ppq/IR/base/graph.py
esp_ppq/IR/base/opdef.py
esp_ppq/api/__init__.py
esp_ppq/api/espdl_interface.py
esp_ppq/api/fsys.py
esp_ppq/api/interface.py
esp_ppq/api/setting.py
esp_ppq/core/README.md
esp_ppq/core/__init__.py
esp_ppq/core/common.py
esp_ppq/core/config.py
esp_ppq/core/data.py
esp_ppq/core/defs.py
esp_ppq/core/ffi.py
esp_ppq/core/quant.py
esp_ppq/core/storage.py
esp_ppq/csrc/export.cc
esp_ppq/csrc/build/.gitignore
esp_ppq/csrc/build/readme.md
esp_ppq/csrc/cpu/common.h
esp_ppq/csrc/cpu/hist_mse.cc
esp_ppq/csrc/cpu/hist_mse.h
esp_ppq/csrc/cuda/PPQ.h
esp_ppq/csrc/cuda/common.cuh
esp_ppq/csrc/cuda/common.h
esp_ppq/csrc/cuda/floating.cu
esp_ppq/csrc/cuda/floating.h
esp_ppq/csrc/cuda/isotone.cc
esp_ppq/csrc/cuda/isotone.h
esp_ppq/csrc/cuda/linear.cu
esp_ppq/csrc/cuda/linear.h
esp_ppq/csrc/cuda/sort.cu
esp_ppq/csrc/cuda/sort.h
esp_ppq/csrc/cuda/test.cu
esp_ppq/csrc/cuda/test.h
esp_ppq/csrc/cuda/train.cu
esp_ppq/csrc/cuda/train.h
esp_ppq/executor/README.md
esp_ppq/executor/__init__.py
esp_ppq/executor/base.py
esp_ppq/executor/torch.py
esp_ppq/executor/op/__init__.py
esp_ppq/executor/op/fp32/fp32_backend.py
esp_ppq/executor/op/ppl_dsp/ppl_dsp_backend.py
esp_ppq/executor/op/ppl_trt/ppl_gpu_backend.py
esp_ppq/executor/op/torch/__init__.py
esp_ppq/executor/op/torch/academic.py
esp_ppq/executor/op/torch/base.py
esp_ppq/executor/op/torch/cuda.py
esp_ppq/executor/op/torch/default.py
esp_ppq/executor/op/torch/dsp.py
esp_ppq/executor/op/torch/espdl.py
esp_ppq/executor/op/torch/extension.py
esp_ppq/executor/op/torch/nxp.py
esp_ppq/executor/op/torch/onnx.py
esp_ppq/lib/README.md
esp_ppq/lib/__init__.py
esp_ppq/lib/common.py
esp_ppq/lib/extension.py
esp_ppq/lib/quant.py
esp_ppq/log/__init__.py
esp_ppq-1.2.4.dist-info/METADATA
esp_ppq-1.2.4.dist-info/WHEEL
esp_ppq-1.2.4.dist-info/licenses/LICENSE
esp_ppq-1.2.4.dist-info/RECORD
