Metadata-Version: 2.4
Name: esp-ppq
Version: 1.2.4
Summary: esp-ppq is an offline quantization tools
Project-URL: Homepage, https://github.com/espressif/esp-ppq
Project-URL: Repository, https://github.com/espressif/esp-ppq
Project-URL: Issues, https://github.com/espressif/esp-dl/issues
License-Expression: Apache-2.0
License-File: LICENSE
Requires-Python: <3.13,>=3.8
Requires-Dist: cryptography>=45.0.4
Requires-Dist: flatbuffers>=25.2.10
Requires-Dist: numpy>=1.24.0
Requires-Dist: onnx<1.18.0,>=1.14.0
Requires-Dist: onnxruntime>=1.19.0
Requires-Dist: onnxsim-prebuilt; python_version >= '3.12'
Requires-Dist: onnxsim>=0.4.36; python_version >= '3.8' and python_version <= '3.11'
Requires-Dist: setuptools>=75.3.0
Requires-Dist: toml
Requires-Dist: tqdm>=4.67.1
Provides-Extra: cpu
Requires-Dist: torch>=2.0.0; extra == 'cpu'
Requires-Dist: torchaudio>=2.0.0; extra == 'cpu'
Requires-Dist: torchvision>=0.15.0; extra == 'cpu'
Provides-Extra: cu124
Requires-Dist: torch>=2.0.0; extra == 'cu124'
Requires-Dist: torchaudio>=2.0.0; extra == 'cu124'
Requires-Dist: torchvision>=0.15.0; extra == 'cu124'
